unifi_official_api/__init__.py
unifi_official_api/_version.py
unifi_official_api/auth.py
unifi_official_api/base.py
unifi_official_api/const.py
unifi_official_api/exceptions.py
unifi_official_api/py.typed
unifi_official_api/network/__init__.py
unifi_official_api/network/client.py
unifi_official_api/network/endpoints/__init__.py
unifi_official_api/network/endpoints/acl.py
unifi_official_api/network/endpoints/clients.py
unifi_official_api/network/endpoints/devices.py
unifi_official_api/network/endpoints/firewall.py
unifi_official_api/network/endpoints/networks.py
unifi_official_api/network/endpoints/resources.py
unifi_official_api/network/endpoints/sites.py
unifi_official_api/network/endpoints/traffic.py
unifi_official_api/network/endpoints/vouchers.py
unifi_official_api/network/endpoints/wifi.py
unifi_official_api/network/models/__init__.py
unifi_official_api/network/models/acl.py
unifi_official_api/network/models/client.py
unifi_official_api/network/models/device.py
unifi_official_api/network/models/firewall.py
unifi_official_api/network/models/network.py
unifi_official_api/network/models/resources.py
unifi_official_api/network/models/site.py
unifi_official_api/network/models/traffic.py
unifi_official_api/network/models/voucher.py
unifi_official_api/network/models/wifi.py
unifi_official_api/protect/__init__.py
unifi_official_api/protect/client.py
unifi_official_api/protect/websocket.py
unifi_official_api/protect/endpoints/__init__.py
unifi_official_api/protect/endpoints/application.py
unifi_official_api/protect/endpoints/cameras.py
unifi_official_api/protect/endpoints/chimes.py
unifi_official_api/protect/endpoints/events.py
unifi_official_api/protect/endpoints/lights.py
unifi_official_api/protect/endpoints/liveviews.py
unifi_official_api/protect/endpoints/nvr.py
unifi_official_api/protect/endpoints/sensors.py
unifi_official_api/protect/endpoints/viewers.py
unifi_official_api/protect/models/__init__.py
unifi_official_api/protect/models/camera.py
unifi_official_api-1.1.0.dist-info/METADATA
unifi_official_api-1.1.0.dist-info/WHEEL
unifi_official_api-1.1.0.dist-info/licenses/LICENSE
unifi_official_api-1.1.0.dist-info/RECORD
