Metadata-Version: 2.4
Name: unifi-official-api
Version: 1.1.0
Summary: Async Python library for the official UniFi Network and Protect APIs
Project-URL: Documentation, https://github.com/ruaan-deysel/unifi-official-api#readme
Project-URL: Issues, https://github.com/ruaan-deysel/unifi-official-api/issues
Project-URL: Source, https://github.com/ruaan-deysel/unifi-official-api
Author: Ruaan Deysel
License-Expression: MIT
License-File: LICENSE
Keywords: api,async,home-assistant,iot,network,protect,smart-home,ubiquiti,unifi
Classifier: Development Status :: 5 - Production/Stable
Classifier: Framework :: AsyncIO
Classifier: Intended Audience :: Developers
Classifier: License :: OSI Approved :: MIT License
Classifier: Operating System :: OS Independent
Classifier: Programming Language :: Python :: 3
Classifier: Programming Language :: Python :: 3.11
Classifier: Programming Language :: Python :: 3.12
Classifier: Programming Language :: Python :: 3.13
Classifier: Programming Language :: Python :: 3.14
Classifier: Topic :: Home Automation
Classifier: Topic :: Software Development :: Libraries :: Python Modules
Classifier: Typing :: Typed
Requires-Python: >=3.11
Requires-Dist: aiohttp>=3.9.0
Requires-Dist: pydantic>=2.0.0
Requires-Dist: yarl>=1.9.0
Provides-Extra: dev
Requires-Dist: aioresponses>=0.7.6; extra == 'dev'
Requires-Dist: mkdocs-material>=9.5.0; extra == 'dev'
Requires-Dist: mkdocs>=1.5.0; extra == 'dev'
Requires-Dist: mkdocstrings[python]>=0.24.0; extra == 'dev'
Requires-Dist: mypy>=1.8.0; extra == 'dev'
Requires-Dist: pre-commit>=3.6.0; extra == 'dev'
Requires-Dist: pytest-asyncio>=0.23.0; extra == 'dev'
Requires-Dist: pytest-cov>=4.1.0; extra == 'dev'
Requires-Dist: pytest>=8.0.0; extra == 'dev'
Requires-Dist: ruff>=0.2.0; extra == 'dev'
Provides-Extra: docs
Requires-Dist: mkdocs-material>=9.5.0; extra == 'docs'
Requires-Dist: mkdocs>=1.5.0; extra == 'docs'
Requires-Dist: mkdocstrings[python]>=0.24.0; extra == 'docs'
Provides-Extra: lint
Requires-Dist: mypy>=1.8.0; extra == 'lint'
Requires-Dist: ruff>=0.2.0; extra == 'lint'
Provides-Extra: test
Requires-Dist: aioresponses>=0.7.6; extra == 'test'
Requires-Dist: pytest-asyncio>=0.23.0; extra == 'test'
Requires-Dist: pytest-cov>=4.1.0; extra == 'test'
Requires-Dist: pytest>=8.0.0; extra == 'test'
